tmpl/__init__.py
tmpl/context.py
tmpl/engine.py
tmpl-1.1.0.dist-info/LICENSE
tmpl-1.1.0.dist-info/METADATA
tmpl-1.1.0.dist-info/WHEEL
tmpl-1.1.0.dist-info/entry_points.txt
tmpl-1.1.0.dist-info/RECORD
